didiator/__init__.py
didiator/dispatchers/__init__.py
didiator/dispatchers/command.py
didiator/dispatchers/query.py
didiator/dispatchers/request.py
didiator/interface/__init__.py
didiator/interface/dispatchers/__init__.py
didiator/interface/dispatchers/command.py
didiator/interface/dispatchers/query.py
didiator/interface/dispatchers/request.py
didiator/interface/entities/__init__.py
didiator/interface/entities/command.py
didiator/interface/entities/event.py
didiator/interface/entities/query.py
didiator/interface/entities/request.py
didiator/interface/exceptions.py
didiator/interface/handlers/__init__.py
didiator/interface/handlers/command.py
didiator/interface/handlers/event.py
didiator/interface/handlers/query.py
didiator/interface/handlers/request.py
didiator/interface/mediator.py
didiator/interface/observers/__init__.py
didiator/interface/observers/event.py
didiator/interface/utils/__init__.py
didiator/interface/utils/di_builder.py
didiator/mediator.py
didiator/middlewares/__init__.py
didiator/middlewares/base.py
didiator/middlewares/di.py
didiator/middlewares/logging.py
didiator/observers/__init__.py
didiator/observers/event.py
didiator/py.typed
didiator/utils/__init__.py
didiator/utils/di_builder.py
didiator-0.3.1.dist-info/LICENSE.rst
didiator-0.3.1.dist-info/METADATA
didiator-0.3.1.dist-info/WHEEL
didiator-0.3.1.dist-info/RECORD
