Metadata-Version: 2.1
Name: didiator
Version: 0.3.1
Summary: A library that implements the Mediator pattern and uses DI library
Home-page: https://github.com/SamWarden/didiator
License: MIT
Keywords: didiator,mediatr,mediator,CQRS,DI,events,ioc
Author: SamWarden
Author-email: SamWardenSad@gmail.com
Maintainer: SamWarden
Maintainer-email: SamWardenSad@gmail.com
Requires-Python: >=3.10,<4.0
Classifier: Intended Audience :: Developers
Classifier: License :: OSI Approved :: MIT License
Classifier: Operating System :: OS Independent
Classifier: Programming Language :: Python :: 3
Classifier: Programming Language :: Python :: 3.10
Classifier: Programming Language :: Python :: 3.11
Classifier: Programming Language :: Python :: 3.10
Classifier: Programming Language :: Python :: 3.11
Classifier: Topic :: Software Development :: Libraries :: Python Modules
Classifier: Typing :: Typed
Provides-Extra: di
Requires-Dist: di[anyio] (>=0.75.0,<0.76.0) ; extra == "di"
Project-URL: Bug Tracker, https://github.com/SamWarden/didiator/issues
Project-URL: Repository, https://github.com/SamWarden/didiator
